README.rst
setup.py
commondata.ee.egg-info/PKG-INFO
commondata.ee.egg-info/SOURCES.txt
commondata.ee.egg-info/dependency_links.txt
commondata.ee.egg-info/namespace_packages.txt
commondata.ee.egg-info/requires.txt
commondata.ee.egg-info/top_level.txt
commondata/ee/__init__.py
commondata/ee/harju.py
commondata/ee/hiiu.py
commondata/ee/idaviru.py
commondata/ee/j6geva.py
commondata/ee/jarva.py
commondata/ee/laane.py
commondata/ee/laaneviru.py
commondata/ee/p6lva.py
commondata/ee/parnu.py
commondata/ee/places.py
commondata/ee/rapla.py
commondata/ee/saare.py
commondata/ee/tartu.py
commondata/ee/v6ru.py
commondata/ee/valga.py
commondata/ee/viljandi.py