Metadata-Version: 1.1
Name: commondata.ee
Version: 0.0.4
Summary: Common data about Estonia
Home-page: https://github.com/lsaffre/commondata-ee
Author: Luc Saffre
Author-email: luc.saffre@gmail.com
License: BSD license
Platform: UNKNOWN
Classifier: Programming Language :: Python
Classifier: Programming Language :: Python :: 2.6
Classifier: Programming Language :: Python :: 2.7
Classifier: Development Status :: 4 - Beta
Classifier: Intended Audience :: Developers
Classifier: License :: OSI Approved :: BSD License
Classifier: Natural Language :: English
Classifier: Operating System :: OS Independent
